pythereum/__init__.py
pythereum/abi.py
pythereum/builders.py
pythereum/common.py
pythereum/dclasses.py
pythereum/exceptions.py
pythereum/gas_managers.py
pythereum/l2_rpc.py
pythereum/rpc.py
pythereum/socket_pool.py
pythereum/utils.py
pythereum-1.2.1.dist-info/LICENSE
pythereum-1.2.1.dist-info/METADATA
pythereum-1.2.1.dist-info/WHEEL
pythereum-1.2.1.dist-info/RECORD
