Metadata-Version: 2.1
Name: pythereum
Version: 1.2.1
Summary: A super fast Ethereum JSON RPC library written in python
Author: gabedonnan
Author-email: 47415809+gabedonnan@users.noreply.github.com
Requires-Python: >=3.11,<4.0
Classifier: Programming Language :: Python :: 3
Classifier: Programming Language :: Python :: 3.11
Requires-Dist: aiohttp (>=3.9.3,<4.0.0)
Requires-Dist: dataclasses-json (>=0.6.4,<0.7.0)
Requires-Dist: eth-account (>=0.10.0,<0.11.0)
Requires-Dist: eth-utils (>=3.0.0,<4.0.0)
Requires-Dist: pycryptodome (>=3.20.0,<4.0.0)
Requires-Dist: pytest (>=7.4.4,<8.0.0)
Requires-Dist: pytest-asyncio (>=0.23.4,<0.24.0)
Requires-Dist: python-dotenv (>=1.0.1,<2.0.0)
Requires-Dist: websockets (>=12.0,<13.0)
